opentsdb_http_client/__init__.py
opentsdb_http_client/http_client.py
opentsdb_http_client-0.2.0.dist-info/METADATA
opentsdb_http_client-0.2.0.dist-info/WHEEL
opentsdb_http_client-0.2.0.dist-info/top_level.txt
opentsdb_http_client-0.2.0.dist-info/RECORD
