Metadata-Version: 2.1
Name: opentsdb-http-client
Version: 0.2.0
Summary: Library for asynchronously uploading metrics to opentsdb http API.
Home-page: UNKNOWN
Author: Jon Nation
Author-email: jnation@lco.global
License: GNU GPL
Platform: UNKNOWN
Requires-Dist: requests
